setup.py
metapdf/__init__.py
metapdf/metapdf.py
metapdf.egg-info/PKG-INFO
metapdf.egg-info/SOURCES.txt
metapdf.egg-info/dependency_links.txt
metapdf.egg-info/requires.txt
metapdf.egg-info/top_level.txt
metapdf.egg-info/zip-safe