Metadata-Version: 1.1
Name: metapdf
Version: 0.3.2
Summary: A lightweight PDF library optimized for metadata extraction and insertion
Home-page: https://github.com/aanari/metapdf
Author: Ali Anari
Author-email: ali@alianari.com
License: MIT
Keywords: python pdf metadata extraction insertion
Platform: UNKNOWN
Classifier: Intended Audience :: Developers
Classifier: Intended Audience :: Information Technology
Classifier: Programming Language :: Python :: 2
Classifier: Operating System :: OS Independent
Classifier: Topic :: Text Processing
Classifier: Development Status :: 3 - Alpha
Classifier: License :: OSI Approved :: MIT License
Classifier: Topic :: Software Development :: Libraries :: Python Modules
